{
  "_class": "group",
  "booleanOperation": -1,
  "clippingMaskMode": 0,
  "do_objectID": "B69CA438-5581-45C1-9CB8-12ABA3209B3F",
  "exportOptions": {
    "_class": "exportOptions",
    "exportFormats": [
    ],
    "includedLayerIds": [
    ],
    "layerOptions": 0,
    "shouldTrim": false
  },
  "frame": {
    "_class": "rect",
    "constrainProportions": false,
    "height": 36,
    "width": 327,
    "x": 16,
    "y": 16
  },
  "hasClickThrough": false,
  "hasClippingMask": false,
  "isFixedToViewport": false,
  "isFlippedHorizontal": false,
  "isFlippedVertical": false,
  "isLocked": false,
  "isVisible": true,
  "layerListExpandedType": 0,
  "layers": [
    {
      "class": "rectangle",
      "id": "F012FF65-0CE0-46CA-98DF-D6C7732C14D7"
    },
    {
      "class": "symbolInstance",
      "id": "A59F7192-579D-47B7-8B4B-848CEAB2E70A"
    },
    {
      "class": "text",
      "id": "512CCDC0-61E1-4863-85A5-17680E77B579"
    },
    {
      "class": "shapeGroup",
      "id": "15F79C1C-24ED-4FFF-B20F-AEBB426750E7"
    }
  ],
  "name": "station-name copy",
  "nameIsFixed": true,
  "resizingConstraint": 63,
  "resizingType": 0,
  "rotation": 0,
  "shouldBreakMaskChain": false,
  "style": {
    "_class": "style",
    "endMarkerType": 0,
    "miterLimit": 10,
    "startMarkerType": 0,
    "windingRule": 1
  },
  "userInfo": {
    "com.animaapp.stc-sketch-plugin": {
      "kModelPropertiesKey": {
      }
    }
  }
}