{
  "_class": "shapePath",
  "booleanOperation": -1,
  "clippingMaskMode": 0,
  "do_objectID": "924CB127-23CB-4599-92CF-DE7AD49B5E8B",
  "edited": true,
  "exportOptions": {
    "_class": "exportOptions",
    "do_objectID": "839C5E5C-575D-444E-8A59-8BB8E23BE997",
    "exportFormats": [
    ],
    "includedLayerIds": [
    ],
    "layerOptions": 0,
    "shouldTrim": false
  },
  "frame": {
    "_class": "rect",
    "constrainProportions": false,
    "do_objectID": "50056D0F-B5D4-44DC-B219-D49982F48C36",
    "height": 33,
    "width": 11,
    "x": 66,
    "y": 88
  },
  "hasClippingMask": false,
  "isClosed": true,
  "isFixedToViewport": false,
  "isFlippedHorizontal": false,
  "isFlippedVertical": false,
  "isLocked": false,
  "isVisible": true,
  "layerListExpandedType": 0,
  "name": "Path",
  "nameIsFixed": false,
  "pointRadiusBehaviour": 1,
  "points": [
    {
      "_class": "curvePoint",
      "cornerRadius": 0,
      "curveFrom": "{0.95452120803027529, 0.95073930272757046}",
      "curveMode": 1,
      "curveTo": "{0.95452120803027529, 0.95073930272757046}",
      "hasCurveFrom": false,
      "hasCurveTo": false,
      "point": "{0.95452120803027529, 0.95073930272757046}"
    },
    {
      "_class": "curvePoint",
      "cornerRadius": 0,
      "curveFrom": "{0.28957218451966626, 1}",
      "curveMode": 1,
      "curveTo": "{0.28957218451966626, 1}",
      "hasCurveFrom": false,
      "hasCurveTo": false,
      "point": "{0.28957218451966626, 1}"
    },
    {
      "_class": "curvePoint",
      "cornerRadius": 0,
      "curveFrom": "{0.28260703985619395, 0.96059144218205639}",
      "curveMode": 1,
      "curveTo": "{0.28260703985619395, 0.96059144218205639}",
      "hasCurveFrom": false,
      "hasCurveTo": false,
      "point": "{0.28260703985619395, 0.96059144218205639}"
    },
    {
      "_class": "curvePoint",
      "cornerRadius": 0,
      "curveFrom": "{0.27790750138841575, 0.11358138617674546}",
      "curveMode": 4,
      "curveTo": "{0.27830939740426497, 0.18685367012400655}",
      "hasCurveFrom": true,
      "hasCurveTo": false,
      "point": "{0.27830939740426497, 0.18685367012400655}"
    },
    {
      "_class": "curvePoint",
      "cornerRadius": 0,
      "curveFrom": "{0, 7.8453696811598689e-06}",
      "curveMode": 4,
      "curveTo": "{0.17506114734698441, 0.044534447686438695}",
      "hasCurveFrom": false,
      "hasCurveTo": true,
      "point": "{0, 7.8453696811598689e-06}"
    },
    {
      "_class": "curvePoint",
      "cornerRadius": 0,
      "curveFrom": "{0, 7.8453696811598689e-06}",
      "curveMode": 4,
      "curveTo": "{0, 7.8453696811598689e-06}",
      "hasCurveFrom": true,
      "hasCurveTo": false,
      "point": "{0, 7.8453696811598689e-06}"
    },
    {
      "_class": "curvePoint",
      "cornerRadius": 0,
      "curveFrom": "{0.66391166153945291, 0.046460682897582491}",
      "curveMode": 3,
      "curveTo": "{0.34425597985628387, -0.0015192362457638858}",
      "hasCurveFrom": true,
      "hasCurveTo": true,
      "point": "{0.60759772596244632, 0.038037103663996867}"
    },
    {
      "_class": "curvePoint",
      "cornerRadius": 0,
      "curveFrom": "{0.85019223264550126, 0.070647685258345222}",
      "curveMode": 3,
      "curveTo": "{0.72037379168376892, 0.054736480039350402}",
      "hasCurveFrom": true,
      "hasCurveTo": true,
      "point": "{0.77831786750116272, 0.061830020446580515}"
    },
    {
      "_class": "curvePoint",
      "cornerRadius": 0,
      "curveFrom": "{0.96193093639566762, 0.17473553859498872}",
      "curveMode": 3,
      "curveTo": "{0.9477042579341074, 0.089416010919141156}",
      "hasCurveFrom": true,
      "hasCurveTo": true,
      "point": "{0.95392842976104086, 0.12646005526800805}"
    },
    {
      "_class": "curvePoint",
      "cornerRadius": 0,
      "curveFrom": "{1.0022944548388846, 0.86877939079296185}",
      "curveMode": 3,
      "curveTo": "{0.98979151504955531, 0.65295838771573456}",
      "hasCurveFrom": true,
      "hasCurveTo": true,
      "point": "{0.99972055105918667, 0.82704569187650057}"
    },
    {
      "_class": "curvePoint",
      "cornerRadius": 0,
      "curveFrom": "{0.95452120803027696, 0.95073930272757046}",
      "curveMode": 4,
      "curveTo": "{0.98707694599391527, 0.91042399204277324}",
      "hasCurveFrom": false,
      "hasCurveTo": true,
      "point": "{0.95452120803027696, 0.95073930272757046}"
    }
  ],
  "resizingConstraint": 63,
  "resizingType": 0,
  "rotation": 0,
  "shouldBreakMaskChain": false,
  "style": {
    "_class": "style",
    "do_objectID": "147407E7-CAD7-4B87-AD55-FE42495917A6",
    "endMarkerType": 0,
    "fills": [
      {
        "_class": "fill",
        "color": {
          "_class": "color",
          "alpha": 1,
          "blue": 0.8862745098039215,
          "green": 0.6196078431372549,
          "red": 0
        },
        "fillType": 0,
        "isEnabled": true,
        "noiseIndex": 0,
        "noiseIntensity": 0,
        "patternFillType": 1,
        "patternTileScale": 1
      }
    ],
    "miterLimit": 10,
    "startMarkerType": 0,
    "windingRule": 1
  }
}