{
  "_class": "artboard",
  "backgroundColor": {
    "_class": "color",
    "alpha": 1,
    "blue": 1,
    "green": 1,
    "red": 1
  },
  "booleanOperation": -1,
  "clippingMaskMode": 0,
  "do_objectID": "08046F5E-00B7-4A0F-A781-B413DA2E5E92",
  "exportOptions": {
    "_class": "exportOptions",
    "exportFormats": [
    ],
    "includedLayerIds": [
    ],
    "layerOptions": 0,
    "shouldTrim": false
  },
  "frame": {
    "_class": "rect",
    "constrainProportions": false,
    "height": 720,
    "width": 360,
    "x": -2774,
    "y": 147
  },
  "hasBackgroundColor": false,
  "hasClickThrough": true,
  "hasClippingMask": false,
  "horizontalRulerData": {
    "_class": "rulerData",
    "base": 0,
    "guides": [
    ]
  },
  "includeBackgroundColorInExport": true,
  "includeInCloudUpload": true,
  "isFixedToViewport": false,
  "isFlippedHorizontal": false,
  "isFlippedVertical": false,
  "isFlowHome": false,
  "isLocked": false,
  "isVisible": true,
  "layerListExpandedType": 2,
  "layers": [
    {
      "class": "rectangle",
      "id": "B830D632-C180-478A-A89E-7593E53CB877"
    },
    {
      "class": "shapePath",
      "id": "0704ACE6-B7C2-42EB-A559-E8588F5EA7D3"
    },
    {
      "class": "shapeGroup",
      "id": "A0C8357C-038D-4CA8-9566-A10133B90EF6"
    },
    {
      "class": "shapeGroup",
      "id": "9D08B919-EB18-419B-BE7B-6E5E39787D4F"
    },
    {
      "class": "text",
      "id": "07162F81-2CE9-4630-9BC4-75C30A2659F0"
    },
    {
      "class": "text",
      "id": "6AED817C-D8FE-4FB9-8934-B9AF1665B28C"
    }
  ],
  "name": "Splash Screen",
  "nameIsFixed": true,
  "presetDictionary": {
    "allowResizedMatching": 0,
    "height": 720,
    "name": "Pixel 2 XL",
    "offersLandscapeVariant": 1,
    "width": 360
  },
  "resizesContent": false,
  "resizingConstraint": 63,
  "resizingType": 0,
  "rotation": 0,
  "shouldBreakMaskChain": true,
  "style": {
    "_class": "style",
    "endMarkerType": 0,
    "miterLimit": 10,
    "startMarkerType": 0,
    "windingRule": 1
  },
  "userInfo": {
    "com.animaapp.stc-sketch-plugin": {
      "kModelPropertiesKey": {
      }
    },
    "io.magicsketch.mirror": {
      "highestQuality": -1
    }
  },
  "verticalRulerData": {
    "_class": "rulerData",
    "base": 0,
    "guides": [
    ]
  }
}