{
  "_class": "group",
  "booleanOperation": -1,
  "clippingMaskMode": 0,
  "do_objectID": "42DA01C1-A297-4D25-97ED-B56D1D1E388F",
  "exportOptions": {
    "_class": "exportOptions",
    "exportFormats": [
    ],
    "includedLayerIds": [
    ],
    "layerOptions": 0,
    "shouldTrim": false
  },
  "frame": {
    "_class": "rect",
    "constrainProportions": true,
    "height": 16,
    "width": 16,
    "x": 103,
    "y": 603
  },
  "hasClickThrough": false,
  "hasClippingMask": false,
  "isFixedToViewport": false,
  "isFlippedHorizontal": false,
  "isFlippedVertical": false,
  "isLocked": false,
  "isVisible": true,
  "layerListExpandedType": 0,
  "layers": [
    {
      "class": "oval",
      "id": "844A5A8B-E49E-4808-B6E3-B82EB8BA8CFE"
    },
    {
      "class": "shapeGroup",
      "id": "EF25138C-058B-4EB7-B10C-A2A819D0CF6C"
    }
  ],
  "name": "Group 2",
  "nameIsFixed": false,
  "resizingConstraint": 63,
  "resizingType": 0,
  "rotation": 0,
  "shouldBreakMaskChain": false,
  "style": {
    "_class": "style",
    "endMarkerType": 0,
    "miterLimit": 10,
    "startMarkerType": 0,
    "windingRule": 1
  },
  "userInfo": {
    "com.animaapp.stc-sketch-plugin": {
      "kModelPropertiesKey": {
        "constraints": {
          "aspectRatio": {
            "constant": 21,
            "enabled": 1,
            "modelID": "constraint_b8520650-5171-4e0a-ad6b-ad1a5b946155",
            "model_class": "ADModelConstraint",
            "model_version": 0.1,
            "multiplier": 21
          },
          "automatic": 1,
          "modelID": "viewConstraints_a71253f3-a818-401d-80d3-37490e1a03cd",
          "model_class": "ADModelViewConstraints",
          "model_version": 0.1,
          "scaleFactor": 1
        }
      }
    }
  }
}